truth_tables/__init__.py
truth_tables/_ast.py
truth_tables/truth_table.py
truth_tables-0.1.1.dist-info/LICENSE.txt
truth_tables-0.1.1.dist-info/METADATA
truth_tables-0.1.1.dist-info/WHEEL
truth_tables-0.1.1.dist-info/top_level.txt
truth_tables-0.1.1.dist-info/RECORD
