Metadata-Version: 2.1
Name: truth_tables
Version: 0.1.1
Summary: Create pretty-printed truth tables from boolean expressions!
Author-email: salt-die <salt-die@protonmail.com>
License: MIT
Project-URL: repository, https://github.com/salt-die/truth_tables
Classifier: Programming Language :: Python :: 3
Classifier: License :: OSI Approved :: MIT License
Classifier: Operating System :: OS Independent
Requires-Python: >=3.11
License-File: LICENSE.txt
Requires-Dist: lark >=1.2.2
